MybatisKuangjiaRumenjiaochengCYuyanBianchengWang/README.md
MybatisKuangjiaRumenjiaochengCYuyanBianchengWang/__init__.py
MybatisKuangjiaRumenjiaochengCYuyanBianchengWang/__main__.py
MybatisKuangjiaRumenjiaochengCYuyanBianchengWang/file.epub
MybatisKuangjiaRumenjiaochengCYuyanBianchengWang/index.html
MybatisKuangjiaRumenjiaochengCYuyanBianchengWang/css/__init__.py
MybatisKuangjiaRumenjiaochengCYuyanBianchengWang/css/annotations.css
MybatisKuangjiaRumenjiaochengCYuyanBianchengWang/css/main.css
MybatisKuangjiaRumenjiaochengCYuyanBianchengWang/css/normalize.css
MybatisKuangjiaRumenjiaochengCYuyanBianchengWang/css/popup.css
MybatisKuangjiaRumenjiaochengCYuyanBianchengWang/font/__init__.py
MybatisKuangjiaRumenjiaochengCYuyanBianchengWang/font/fontello.eot
MybatisKuangjiaRumenjiaochengCYuyanBianchengWang/font/fontello.svg
MybatisKuangjiaRumenjiaochengCYuyanBianchengWang/font/fontello.ttf
MybatisKuangjiaRumenjiaochengCYuyanBianchengWang/font/fontello.woff
MybatisKuangjiaRumenjiaochengCYuyanBianchengWang/img/__init__.py
MybatisKuangjiaRumenjiaochengCYuyanBianchengWang/img/annotator-glyph-sprite.png
MybatisKuangjiaRumenjiaochengCYuyanBianchengWang/img/annotator-icon-sprite.png
MybatisKuangjiaRumenjiaochengCYuyanBianchengWang/img/apple-touch-icon.png
MybatisKuangjiaRumenjiaochengCYuyanBianchengWang/img/cancelfullscreen.png
MybatisKuangjiaRumenjiaochengCYuyanBianchengWang/img/close.png
MybatisKuangjiaRumenjiaochengCYuyanBianchengWang/img/fullscreen.png
MybatisKuangjiaRumenjiaochengCYuyanBianchengWang/img/loader.gif
MybatisKuangjiaRumenjiaochengCYuyanBianchengWang/img/menu-icon.png
MybatisKuangjiaRumenjiaochengCYuyanBianchengWang/img/save.png
MybatisKuangjiaRumenjiaochengCYuyanBianchengWang/img/saved.png
MybatisKuangjiaRumenjiaochengCYuyanBianchengWang/img/settings-s.png
MybatisKuangjiaRumenjiaochengCYuyanBianchengWang/img/settings.png
MybatisKuangjiaRumenjiaochengCYuyanBianchengWang/img/star.png
MybatisKuangjiaRumenjiaochengCYuyanBianchengWang/js/__init__.py
mybatis_kuangjia_rumenjiaocheng_c_yuyan_biancheng_wang-2024.3.5.0.dist-info/METADATA
mybatis_kuangjia_rumenjiaocheng_c_yuyan_biancheng_wang-2024.3.5.0.dist-info/WHEEL
mybatis_kuangjia_rumenjiaocheng_c_yuyan_biancheng_wang-2024.3.5.0.dist-info/entry_points.txt
mybatis_kuangjia_rumenjiaocheng_c_yuyan_biancheng_wang-2024.3.5.0.dist-info/top_level.txt
mybatis_kuangjia_rumenjiaocheng_c_yuyan_biancheng_wang-2024.3.5.0.dist-info/RECORD
